{
  "$schema": "https://vega.github.io/schema/vega/v4.json",
  "width": 960,
  "height": 500,
  "autosize": "none",
  "data": [
    {
      "name": "LossesOccured",
      "url": "https://raw.githubusercontent.com/veperuma/vega/master/losses2015_transformed.csv",
      "format": {"type": "csv", "parse": "auto"},
      "transform": [{
  "type": "aggregate",
  "fields": ["Amount"],
  "groupby": ["State_Code","State_Abv"],
  "ops": ["sum"],
  "as": ["Amount"]
}]
    },
    {
      "name": "StatesPresent",
      "url": "https://raw.githubusercontent.com/veperuma/vega/master/us-10m.json",
      "format": {"type": "topojson", "feature": "states"},
      "transform": [
        { "type": "lookup", "from": "LossesOccured", "key": "State_Code", "fields": ["id"], "values": ["State_Code","Amount","State_Abv"] },
        { "type": "filter", "expr": "datum.Amount != null" }
      ]
    }
  ],

  "projections": [
    {
      "name": "projection",
      "type": "albersUsa"
    }
  ],

  "scales": [
    {
      "name": "color",
      "type": "quantize",
      "domain": [0, 50000000],
      "range": {"scheme": "blues", "count": 50}
    }
  ],

  "legends": [
    {
      "fill": "color",
      "orient": "bottom-right",
      "title": "Amount"
    }
  ],

  "marks": [
    {
      "type": "shape",
      "from": {"data": "StatesPresent"},
      "encode": {
        "enter": { "tooltip": {"signal": "'State:'+ datum.State_Abv +' Amount:' + format(datum.Amount,',d')"}},
        "update": { "fill": {"scale": "color", "field": "Amount"} },
        "hover": { "fill": {"value": "red"} }
      },
      "transform": [
        { "type": "geoshape", "projection": "projection" }

      ]
    }
  ]
}
